LICENSE.txt
README.md
setup.cfg
setup.py
test/__init__.py
test/sanity_test.py
test/test_analytics_data.py
test/test_api_gateway_error_response.py
test/test_batch_execution_summary.py
test/test_brokerage_data.py
test/test_brokerage_taxes.py
test/test_brokerage_wrapper_data.py
test/test_cancel_or_exit_multi_order_data.py
test/test_cancel_or_exit_multi_order_response.py
test/test_cancel_or_exit_order_error_data.py
test/test_cancel_order_data.py
test/test_cancel_order_response.py
test/test_cancel_order_v3_response.py
test/test_charge_api.py
test/test_convert_position_data.py
test/test_convert_position_request.py
test/test_convert_position_response.py
test/test_depth.py
test/test_depth_map.py
test/test_dp_plan.py
test/test_exchange_timing_data.py
test/test_get_brokerage_response.py
test/test_get_exchange_timing_response.py
test/test_get_full_market_quote_response.py
test/test_get_gtt_order_response.py
test/test_get_historical_candle_response.py
test/test_get_holdings_response.py
test/test_get_holiday_response.py
test/test_get_intra_day_candle_response.py
test/test_get_market_quote_last_traded_price_response.py
test/test_get_market_quote_ohlc_response.py
test/test_get_market_status_response.py
test/test_get_option_chain_response.py
test/test_get_option_contract_response.py
test/test_get_order_book_response.py
test/test_get_order_details_response.py
test/test_get_order_response.py
test/test_get_position_response.py
test/test_get_profile_response.py
test/test_get_profit_and_loss_charges_response.py
test/test_get_trade_response.py
test/test_get_trade_wise_profit_and_loss_data_response.py
test/test_get_trade_wise_profit_and_loss_meta_data_response.py
test/test_get_user_fund_margin_response.py
test/test_gtt_cancel_order_request.py
test/test_gtt_modify_order_request.py
test/test_gtt_order_data.py
test/test_gtt_order_details.py
test/test_gtt_place_order_request.py
test/test_gtt_rule.py
test/test_gtt_trigger_order_response.py
test/test_historical_candle_data.py
upstox_python_sdk.egg-info/PKG-INFO
upstox_python_sdk.egg-info/SOURCES.txt
upstox_python_sdk.egg-info/dependency_links.txt
upstox_python_sdk.egg-info/requires.txt
upstox_python_sdk.egg-info/top_level.txt