Metadata-Version: 2.1
Name: upstox-python-sdk
Version: 2.19.0
Summary: Upstox Developer API
Home-page: https://github.com/upstox/upstox-python
License: MIT
Keywords: Upstox Developer API
Platform: UNKNOWN
License-File: LICENSE.txt
